tdp2xlsx/__init__.py
tdp2xlsx/tdpxlsx.py
tdp2xlsx-0.1.0.dist-info/licenses/LICENSE
tdp2xlsx-0.1.0.dist-info/WHEEL
tdp2xlsx-0.1.0.dist-info/METADATA
tdp2xlsx-0.1.0.dist-info/RECORD
