Metadata-Version: 2.4
Name: tdp2xlsx
Version: 0.1.0
Summary: A template Python module
Home-page: https://github.com/IslasGECI/tdp2xlsx
Author: Ciencia de Datos • GECI
Author-email: ciencia.datos@islas.org.mx
Requires-Python: >=3.9
Classifier: License :: OSI Approved :: GNU General Public License v3 or later (GPLv3+)
License-File: LICENSE
